nors/nors.cpython-38-x86_64-linux-gnu.so
nors/__init__.py
nors-0.1.0.dist-info/METADATA
nors-0.1.0.dist-info/RECORD
nors-0.1.0.dist-info/top_level.txt
nors-0.1.0.dist-info/WHEEL
